{"name":"Program","children":{"Statement":[{"name":"Statement","children":{"printStatement":[{"name":"printStatement","children":{"Print":[{"image":"print","startOffset":0,"endOffset":4,"startLine":1,"endLine":1,"startColumn":1,"endColumn":5,"tokenTypeIdx":7,"tokenType":{"name":"Print","PATTERN":{},"tokenTypeIdx":7,"CATEGORIES":[],"categoryMatches":[],"categoryMatchesMap":{},"isParent":false}}],"LeftParenthis":[{"image":"(","startOffset":5,"endOffset":5,"startLine":1,"endLine":1,"startColumn":6,"endColumn":6,"tokenTypeIdx":20,"tokenType":{"name":"LeftParenthis","PATTERN":{},"tokenTypeIdx":20,"CATEGORIES":[],"categoryMatches":[],"categoryMatchesMap":{},"isParent":false}}],"Expression":[{"name":"Expression","children":{"Operand":[{"name":"Operand","children":{"OperandSimple":[{"name":"OperandSimple","children":{"ParenthisExpression":[{"name":"ParenthisExpression","children":{"LeftParenthis":[{"image":"(","startOffset":6,"endOffset":6,"startLine":1,"endLine":1,"startColumn":7,"endColumn":7,"tokenTypeIdx":20,"tokenType":{"name":"LeftParenthis","PATTERN":{},"tokenTypeIdx":20,"CATEGORIES":[],"categoryMatches":[],"categoryMatchesMap":{},"isParent":false}}],"Expression":[{"name":"Expression","children":{"Operand":[{"name":"Operand","children":{"OperandSimple":[{"name":"OperandSimple","children":{"ParenthisExpression":[{"name":"ParenthisExpression","children":{"LeftParenthis":[{"image":"(","startOffset":7,"endOffset":7,"startLine":1,"endLine":1,"startColumn":8,"endColumn":8,"tokenTypeIdx":20,"tokenType":{"name":"LeftParenthis","PATTERN":{},"tokenTypeIdx":20,"CATEGORIES":[],"categoryMatches":[],"categoryMatchesMap":{},"isParent":false}}],"Expression":[{"name":"Expression","children":{"Operand":[{"name":"Operand","children":{"OperandSimple":[{"name":"OperandSimple","children":{"Identifier":[{"image":"b","startOffset":8,"endOffset":8,"startLine":1,"endLine":1,"startColumn":9,"endColumn":9,"tokenTypeIdx":3,"tokenType":{"name":"Identifier","PATTERN":{},"tokenTypeIdx":3,"CATEGORIES":[],"categoryMatches":[],"categoryMatchesMap":{},"isParent":false}}]}}]}}]}}],"RightParenthis":[{"image":")","startOffset":9,"endOffset":9,"startLine":1,"endLine":1,"startColumn":10,"endColumn":10,"tokenTypeIdx":21,"tokenType":{"name":"RightParenthis","PATTERN":{},"tokenTypeIdx":21,"CATEGORIES":[],"categoryMatches":[],"categoryMatchesMap":{},"isParent":false}}]}}]}}]}},{"name":"Operand","children":{"OperandWithUnary":[{"name":"OperandWithUnary","children":{"Minus":[{"image":"-","startOffset":13,"endOffset":13,"startLine":1,"endLine":1,"startColumn":14,"endColumn":14,"tokenTypeIdx":23,"tokenType":{"name":"Minus","PATTERN":{},"tokenTypeIdx":23,"CATEGORIES":[],"categoryMatches":[],"categoryMatchesMap":{},"isParent":false}}],"OperandSimple":[{"name":"OperandSimple","children":{"Identifier":[{"image":"c","startOffset":14,"endOffset":14,"startLine":1,"endLine":1,"startColumn":15,"endColumn":15,"tokenTypeIdx":3,"tokenType":{"name":"Identifier","PATTERN":{},"tokenTypeIdx":3,"CATEGORIES":[],"categoryMatches":[],"categoryMatchesMap":{},"isParent":false}}]}}]}}]}}],"Operator":[{"name":"Operator","children":{"Plus":[{"image":"+","startOffset":11,"endOffset":11,"startLine":1,"endLine":1,"startColumn":12,"endColumn":12,"tokenTypeIdx":22,"tokenType":{"name":"Plus","PATTERN":{},"tokenTypeIdx":22,"CATEGORIES":[],"categoryMatches":[],"categoryMatchesMap":{},"isParent":false}}]}}]}}],"RightParenthis":[{"image":")","startOffset":15,"endOffset":15,"startLine":1,"endLine":1,"startColumn":16,"endColumn":16,"tokenTypeIdx":21,"tokenType":{"name":"RightParenthis","PATTERN":{},"tokenTypeIdx":21,"CATEGORIES":[],"categoryMatches":[],"categoryMatchesMap":{},"isParent":false}}]}}]}}]}}]}}],"RightParenthis":[{"image":")","startOffset":16,"endOffset":16,"startLine":1,"endLine":1,"startColumn":17,"endColumn":17,"tokenTypeIdx":21,"tokenType":{"name":"RightParenthis","PATTERN":{},"tokenTypeIdx":21,"CATEGORIES":[],"categoryMatches":[],"categoryMatchesMap":{},"isParent":false}}]}}]}},{"name":"Statement","children":{"assignStatement":[{"name":"assignStatement","children":{"Identifier":[{"image":"b","startOffset":19,"endOffset":19,"startLine":2,"endLine":2,"startColumn":1,"endColumn":1,"tokenTypeIdx":3,"tokenType":{"name":"Identifier","PATTERN":{},"tokenTypeIdx":3,"CATEGORIES":[],"categoryMatches":[],"categoryMatchesMap":{},"isParent":false}}],"Equal":[{"image":"=","startOffset":21,"endOffset":21,"startLine":2,"endLine":2,"startColumn":3,"endColumn":3,"tokenTypeIdx":17,"tokenType":{"name":"Equal","PATTERN":{},"tokenTypeIdx":17,"CATEGORIES":[],"categoryMatches":[],"categoryMatchesMap":{},"isParent":false}}],"Expression":[{"name":"Expression","children":{"Operand":[{"name":"Operand","children":{"OperandSimple":[{"name":"OperandSimple","children":{"Number":[{"name":"Number","children":{"Real":[{"image":"2 ","startOffset":23,"endOffset":24,"startLine":2,"endLine":2,"startColumn":5,"endColumn":6,"tokenTypeIdx":6,"tokenType":{"name":"Real","PATTERN":{},"tokenTypeIdx":6,"CATEGORIES":[],"categoryMatches":[],"categoryMatchesMap":{},"isParent":false}}]}}]}}]}}]}}]}}]}},{"name":"Statement","children":{"scanStatement":[{"name":"scanStatement","children":{"Scan":[{"image":"scan","startOffset":29,"endOffset":32,"startLine":4,"endLine":4,"startColumn":1,"endColumn":4,"tokenTypeIdx":8,"tokenType":{"name":"Scan","PATTERN":{},"tokenTypeIdx":8,"CATEGORIES":[],"categoryMatches":[],"categoryMatchesMap":{},"isParent":false}}],"LeftParenthis":[{"image":"(","startOffset":33,"endOffset":33,"startLine":4,"endLine":4,"startColumn":5,"endColumn":5,"tokenTypeIdx":20,"tokenType":{"name":"LeftParenthis","PATTERN":{},"tokenTypeIdx":20,"CATEGORIES":[],"categoryMatches":[],"categoryMatchesMap":{},"isParent":false}}],"Identifier":[{"image":"c","startOffset":34,"endOffset":34,"startLine":4,"endLine":4,"startColumn":6,"endColumn":6,"tokenTypeIdx":3,"tokenType":{"name":"Identifier","PATTERN":{},"tokenTypeIdx":3,"CATEGORIES":[],"categoryMatches":[],"categoryMatchesMap":{},"isParent":false}}],"RightParenthis":[{"image":")","startOffset":35,"endOffset":35,"startLine":4,"endLine":4,"startColumn":7,"endColumn":7,"tokenTypeIdx":21,"tokenType":{"name":"RightParenthis","PATTERN":{},"tokenTypeIdx":21,"CATEGORIES":[],"categoryMatches":[],"categoryMatchesMap":{},"isParent":false}}]}}]}},{"name":"Statement","children":{"ifStatement":[{"name":"ifStatement","children":{"If":[{"image":"if","startOffset":38,"endOffset":39,"startLine":5,"endLine":5,"startColumn":1,"endColumn":2,"tokenTypeIdx":14,"tokenType":{"name":"If","PATTERN":{},"tokenTypeIdx":14,"CATEGORIES":[],"categoryMatches":[],"categoryMatchesMap":{},"isParent":false}}],"Expression":[{"name":"Expression","children":{"Operand":[{"name":"Operand","children":{"OperandSimple":[{"name":"OperandSimple","children":{"Identifier":[{"image":"a","startOffset":41,"endOffset":41,"startLine":5,"endLine":5,"startColumn":4,"endColumn":4,"tokenTypeIdx":3,"tokenType":{"name":"Identifier","PATTERN":{},"tokenTypeIdx":3,"CATEGORIES":[],"categoryMatches":[],"categoryMatchesMap":{},"isParent":false}}]}}]}},{"name":"Operand","children":{"OperandSimple":[{"name":"OperandSimple","children":{"Identifier":[{"image":"b","startOffset":46,"endOffset":46,"startLine":5,"endLine":5,"startColumn":9,"endColumn":9,"tokenTypeIdx":3,"tokenType":{"name":"Identifier","PATTERN":{},"tokenTypeIdx":3,"CATEGORIES":[],"categoryMatches":[],"categoryMatchesMap":{},"isParent":false}}]}}]}}],"Operator":[{"name":"Operator","children":{"Or":[{"image":"||","startOffset":43,"endOffset":44,"startLine":5,"endLine":5,"startColumn":6,"endColumn":7,"tokenTypeIdx":27,"tokenType":{"name":"Or","PATTERN":{},"tokenTypeIdx":27,"CATEGORIES":[],"categoryMatches":[],"categoryMatchesMap":{},"isParent":false}}]}}]}}],"Then":[{"image":"then","startOffset":48,"endOffset":51,"startLine":5,"endLine":5,"startColumn":11,"endColumn":14,"tokenTypeIdx":15,"tokenType":{"name":"Then","PATTERN":{},"tokenTypeIdx":15,"CATEGORIES":[],"categoryMatches":[],"categoryMatchesMap":{},"isParent":false}}],"Statement":[{"name":"Statement","children":{"assignStatement":[{"name":"assignStatement","children":{"Identifier":[{"image":"c","startOffset":58,"endOffset":58,"startLine":6,"endLine":6,"startColumn":5,"endColumn":5,"tokenTypeIdx":3,"tokenType":{"name":"Identifier","PATTERN":{},"tokenTypeIdx":3,"CATEGORIES":[],"categoryMatches":[],"categoryMatchesMap":{},"isParent":false}}],"Equal":[{"image":"=","startOffset":60,"endOffset":60,"startLine":6,"endLine":6,"startColumn":7,"endColumn":7,"tokenTypeIdx":17,"tokenType":{"name":"Equal","PATTERN":{},"tokenTypeIdx":17,"CATEGORIES":[],"categoryMatches":[],"categoryMatchesMap":{},"isParent":false}}],"Expression":[{"name":"Expression","children":{"Operand":[{"name":"Operand","children":{"OperandSimple":[{"name":"OperandSimple","children":{"Identifier":[{"image":"a","startOffset":62,"endOffset":62,"startLine":6,"endLine":6,"startColumn":9,"endColumn":9,"tokenTypeIdx":3,"tokenType":{"name":"Identifier","PATTERN":{},"tokenTypeIdx":3,"CATEGORIES":[],"categoryMatches":[],"categoryMatchesMap":{},"isParent":false}}]}}]}}]}}]}}]}},{"name":"Statement","children":{"ifStatement":[{"name":"ifStatement","children":{"If":[{"image":"if","startOffset":69,"endOffset":70,"startLine":7,"endLine":7,"startColumn":5,"endColumn":6,"tokenTypeIdx":14,"tokenType":{"name":"If","PATTERN":{},"tokenTypeIdx":14,"CATEGORIES":[],"categoryMatches":[],"categoryMatchesMap":{},"isParent":false}}],"Expression":[{"name":"Expression","children":{"Operand":[{"name":"Operand","children":{"OperandSimple":[{"name":"OperandSimple","children":{"Identifier":[{"image":"a","startOffset":72,"endOffset":72,"startLine":7,"endLine":7,"startColumn":8,"endColumn":8,"tokenTypeIdx":3,"tokenType":{"name":"Identifier","PATTERN":{},"tokenTypeIdx":3,"CATEGORIES":[],"categoryMatches":[],"categoryMatchesMap":{},"isParent":false}}]}}]}}]}}],"Then":[{"image":"then","startOffset":74,"endOffset":77,"startLine":7,"endLine":7,"startColumn":10,"endColumn":13,"tokenTypeIdx":15,"tokenType":{"name":"Then","PATTERN":{},"tokenTypeIdx":15,"CATEGORIES":[],"categoryMatches":[],"categoryMatchesMap":{},"isParent":false}}],"Statement":[{"name":"Statement","children":{"assignStatement":[{"name":"assignStatement","children":{"Identifier":[{"image":"a","startOffset":89,"endOffset":89,"startLine":8,"endLine":8,"startColumn":9,"endColumn":9,"tokenTypeIdx":3,"tokenType":{"name":"Identifier","PATTERN":{},"tokenTypeIdx":3,"CATEGORIES":[],"categoryMatches":[],"categoryMatchesMap":{},"isParent":false}}],"Equal":[{"image":"=","startOffset":91,"endOffset":91,"startLine":8,"endLine":8,"startColumn":11,"endColumn":11,"tokenTypeIdx":17,"tokenType":{"name":"Equal","PATTERN":{},"tokenTypeIdx":17,"CATEGORIES":[],"categoryMatches":[],"categoryMatchesMap":{},"isParent":false}}],"Expression":[{"name":"Expression","children":{"Operand":[{"name":"Operand","children":{"OperandSimple":[{"name":"OperandSimple","children":{"Identifier":[{"image":"b","startOffset":93,"endOffset":93,"startLine":8,"endLine":8,"startColumn":13,"endColumn":13,"tokenTypeIdx":3,"tokenType":{"name":"Identifier","PATTERN":{},"tokenTypeIdx":3,"CATEGORIES":[],"categoryMatches":[],"categoryMatchesMap":{},"isParent":false}}]}}]}}]}}]}}]}}],"Fi":[{"image":"fi","startOffset":100,"endOffset":101,"startLine":9,"endLine":9,"startColumn":5,"endColumn":6,"tokenTypeIdx":16,"tokenType":{"name":"Fi","PATTERN":{},"tokenTypeIdx":16,"CATEGORIES":[],"categoryMatches":[],"categoryMatchesMap":{},"isParent":false}}]}}]}},{"name":"Statement","children":{"assignStatement":[{"name":"assignStatement","children":{"Identifier":[{"image":"b","startOffset":108,"endOffset":108,"startLine":10,"endLine":10,"startColumn":5,"endColumn":5,"tokenTypeIdx":3,"tokenType":{"name":"Identifier","PATTERN":{},"tokenTypeIdx":3,"CATEGORIES":[],"categoryMatches":[],"categoryMatchesMap":{},"isParent":false}}],"Equal":[{"image":"=","startOffset":110,"endOffset":110,"startLine":10,"endLine":10,"startColumn":7,"endColumn":7,"tokenTypeIdx":17,"tokenType":{"name":"Equal","PATTERN":{},"tokenTypeIdx":17,"CATEGORIES":[],"categoryMatches":[],"categoryMatchesMap":{},"isParent":false}}],"Expression":[{"name":"Expression","children":{"Operand":[{"name":"Operand","children":{"OperandSimple":[{"name":"OperandSimple","children":{"Identifier":[{"image":"c","startOffset":112,"endOffset":112,"startLine":10,"endLine":10,"startColumn":9,"endColumn":9,"tokenTypeIdx":3,"tokenType":{"name":"Identifier","PATTERN":{},"tokenTypeIdx":3,"CATEGORIES":[],"categoryMatches":[],"categoryMatchesMap":{},"isParent":false}}]}}]}}]}}]}}]}}],"Fi":[{"image":"fi","startOffset":115,"endOffset":116,"startLine":11,"endLine":11,"startColumn":1,"endColumn":2,"tokenTypeIdx":16,"tokenType":{"name":"Fi","PATTERN":{},"tokenTypeIdx":16,"CATEGORIES":[],"categoryMatches":[],"categoryMatchesMap":{},"isParent":false}}]}}]}},{"name":"Statement","children":{"forStatement":[{"name":"forStatement","children":{"For":[{"image":"for","startOffset":121,"endOffset":123,"startLine":13,"endLine":13,"startColumn":1,"endColumn":3,"tokenTypeIdx":9,"tokenType":{"name":"For","PATTERN":{},"tokenTypeIdx":9,"CATEGORIES":[],"categoryMatches":[],"categoryMatchesMap":{},"isParent":false}}],"assignStatement":[{"name":"assignStatement","children":{"Identifier":[{"image":"i","startOffset":125,"endOffset":125,"startLine":13,"endLine":13,"startColumn":5,"endColumn":5,"tokenTypeIdx":3,"tokenType":{"name":"Identifier","PATTERN":{},"tokenTypeIdx":3,"CATEGORIES":[],"categoryMatches":[],"categoryMatchesMap":{},"isParent":false}}],"Equal":[{"image":"=","startOffset":127,"endOffset":127,"startLine":13,"endLine":13,"startColumn":7,"endColumn":7,"tokenTypeIdx":17,"tokenType":{"name":"Equal","PATTERN":{},"tokenTypeIdx":17,"CATEGORIES":[],"categoryMatches":[],"categoryMatchesMap":{},"isParent":false}}],"Expression":[{"name":"Expression","children":{"Operand":[{"name":"Operand","children":{"OperandSimple":[{"name":"OperandSimple","children":{"Number":[{"name":"Number","children":{"Real":[{"image":"1 ","startOffset":129,"endOffset":130,"startLine":13,"endLine":13,"startColumn":9,"endColumn":10,"tokenTypeIdx":6,"tokenType":{"name":"Real","PATTERN":{},"tokenTypeIdx":6,"CATEGORIES":[],"categoryMatches":[],"categoryMatchesMap":{},"isParent":false}}]}}]}}]}}]}}]}}],"To":[{"image":"to","startOffset":131,"endOffset":132,"startLine":13,"endLine":13,"startColumn":11,"endColumn":12,"tokenTypeIdx":10,"tokenType":{"name":"To","PATTERN":{},"tokenTypeIdx":10,"CATEGORIES":[],"categoryMatches":[],"categoryMatchesMap":{},"isParent":false}}],"Expression":[{"name":"Expression","children":{"Operand":[{"name":"Operand","children":{"OperandSimple":[{"name":"OperandSimple","children":{"Number":[{"name":"Number","children":{"Real":[{"image":"10 ","startOffset":134,"endOffset":136,"startLine":13,"endLine":13,"startColumn":14,"endColumn":16,"tokenTypeIdx":6,"tokenType":{"name":"Real","PATTERN":{},"tokenTypeIdx":6,"CATEGORIES":[],"categoryMatches":[],"categoryMatchesMap":{},"isParent":false}}]}}]}}]}}]}},{"name":"Expression","children":{"Operand":[{"name":"Operand","children":{"OperandSimple":[{"name":"OperandSimple","children":{"Number":[{"name":"Number","children":{"Real":[{"image":"1 ","startOffset":140,"endOffset":141,"startLine":13,"endLine":13,"startColumn":20,"endColumn":21,"tokenTypeIdx":6,"tokenType":{"name":"Real","PATTERN":{},"tokenTypeIdx":6,"CATEGORIES":[],"categoryMatches":[],"categoryMatchesMap":{},"isParent":false}}]}}]}}]}}]}},{"name":"Expression","children":{"Operand":[{"name":"Operand","children":{"OperandSimple":[{"name":"OperandSimple","children":{"Identifier":[{"image":"i","startOffset":148,"endOffset":148,"startLine":13,"endLine":13,"startColumn":28,"endColumn":28,"tokenTypeIdx":3,"tokenType":{"name":"Identifier","PATTERN":{},"tokenTypeIdx":3,"CATEGORIES":[],"categoryMatches":[],"categoryMatchesMap":{},"isParent":false}}]}}]}},{"name":"Operand","children":{"OperandSimple":[{"name":"OperandSimple","children":{"Number":[{"name":"Number","children":{"Real":[{"image":"10 ","startOffset":152,"endOffset":154,"startLine":13,"endLine":13,"startColumn":32,"endColumn":34,"tokenTypeIdx":6,"tokenType":{"name":"Real","PATTERN":{},"tokenTypeIdx":6,"CATEGORIES":[],"categoryMatches":[],"categoryMatchesMap":{},"isParent":false}}]}}]}}]}}],"Operator":[{"name":"Operator","children":{"Plus":[{"image":"+","startOffset":150,"endOffset":150,"startLine":13,"endLine":13,"startColumn":30,"endColumn":30,"tokenTypeIdx":22,"tokenType":{"name":"Plus","PATTERN":{},"tokenTypeIdx":22,"CATEGORIES":[],"categoryMatches":[],"categoryMatchesMap":{},"isParent":false}}]}}]}}],"By":[{"image":"by","startOffset":137,"endOffset":138,"startLine":13,"endLine":13,"startColumn":17,"endColumn":18,"tokenTypeIdx":11,"tokenType":{"name":"By","PATTERN":{},"tokenTypeIdx":11,"CATEGORIES":[],"categoryMatches":[],"categoryMatchesMap":{},"isParent":false}}],"While":[{"image":"while","startOffset":142,"endOffset":146,"startLine":13,"endLine":13,"startColumn":22,"endColumn":26,"tokenTypeIdx":12,"tokenType":{"name":"While","PATTERN":{},"tokenTypeIdx":12,"CATEGORIES":[],"categoryMatches":[],"categoryMatchesMap":{},"isParent":false}}],"Statement":[{"name":"Statement","children":{"assignStatement":[{"name":"assignStatement","children":{"Identifier":[{"image":"z","startOffset":161,"endOffset":161,"startLine":14,"endLine":14,"startColumn":5,"endColumn":5,"tokenTypeIdx":3,"tokenType":{"name":"Identifier","PATTERN":{},"tokenTypeIdx":3,"CATEGORIES":[],"categoryMatches":[],"categoryMatchesMap":{},"isParent":false}}],"Equal":[{"image":"=","startOffset":163,"endOffset":163,"startLine":14,"endLine":14,"startColumn":7,"endColumn":7,"tokenTypeIdx":17,"tokenType":{"name":"Equal","PATTERN":{},"tokenTypeIdx":17,"CATEGORIES":[],"categoryMatches":[],"categoryMatchesMap":{},"isParent":false}}],"Expression":[{"name":"Expression","children":{"Operand":[{"name":"Operand","children":{"OperandSimple":[{"name":"OperandSimple","children":{"Number":[{"name":"Number","children":{"Real":[{"image":"10","startOffset":165,"endOffset":166,"startLine":14,"endLine":14,"startColumn":9,"endColumn":10,"tokenTypeIdx":6,"tokenType":{"name":"Real","PATTERN":{},"tokenTypeIdx":6,"CATEGORIES":[],"categoryMatches":[],"categoryMatchesMap":{},"isParent":false}}]}}]}}]}}]}}]}}]}},{"name":"Statement","children":{"assignStatement":[{"name":"assignStatement","children":{"Identifier":[{"image":"zn","startOffset":173,"endOffset":174,"startLine":15,"endLine":15,"startColumn":5,"endColumn":6,"tokenTypeIdx":3,"tokenType":{"name":"Identifier","PATTERN":{},"tokenTypeIdx":3,"CATEGORIES":[],"categoryMatches":[],"categoryMatchesMap":{},"isParent":false}}],"Equal":[{"image":"=","startOffset":176,"endOffset":176,"startLine":15,"endLine":15,"startColumn":8,"endColumn":8,"tokenTypeIdx":17,"tokenType":{"name":"Equal","PATTERN":{},"tokenTypeIdx":17,"CATEGORIES":[],"categoryMatches":[],"categoryMatchesMap":{},"isParent":false}}],"Expression":[{"name":"Expression","children":{"Operand":[{"name":"Operand","children":{"OperandSimple":[{"name":"OperandSimple","children":{"Identifier":[{"image":"z","startOffset":178,"endOffset":178,"startLine":15,"endLine":15,"startColumn":10,"endColumn":10,"tokenTypeIdx":3,"tokenType":{"name":"Identifier","PATTERN":{},"tokenTypeIdx":3,"CATEGORIES":[],"categoryMatches":[],"categoryMatchesMap":{},"isParent":false}}]}}]}},{"name":"Operand","children":{"OperandSimple":[{"name":"OperandSimple","children":{"Number":[{"name":"Number","children":{"Real":[{"image":"1","startOffset":182,"endOffset":182,"startLine":15,"endLine":15,"startColumn":14,"endColumn":14,"tokenTypeIdx":6,"tokenType":{"name":"Real","PATTERN":{},"tokenTypeIdx":6,"CATEGORIES":[],"categoryMatches":[],"categoryMatchesMap":{},"isParent":false}}]}}]}}]}}],"Operator":[{"name":"Operator","children":{"Plus":[{"image":"+","startOffset":180,"endOffset":180,"startLine":15,"endLine":15,"startColumn":12,"endColumn":12,"tokenTypeIdx":22,"tokenType":{"name":"Plus","PATTERN":{},"tokenTypeIdx":22,"CATEGORIES":[],"categoryMatches":[],"categoryMatchesMap":{},"isParent":false}}]}}]}}]}}]}}],"Rof":[{"image":"rof","startOffset":185,"endOffset":187,"startLine":16,"endLine":16,"startColumn":1,"endColumn":3,"tokenTypeIdx":13,"tokenType":{"name":"Rof","PATTERN":{},"tokenTypeIdx":13,"CATEGORIES":[],"categoryMatches":[],"categoryMatchesMap":{},"isParent":false}}]}}]}}]}}